dreimac/__init__.py
dreimac/_version.py
dreimac/circularcoords.py
dreimac/combinatorial.py
dreimac/complexprojectivecoords.py
dreimac/emcoords.py
dreimac/lenscoords.py
dreimac/plotting_utils.py
dreimac/projectivecoords.py
dreimac/toroidalcoords.py
dreimac/utils.py
dreimac-0.3.2.dist-info/LICENSE
dreimac-0.3.2.dist-info/METADATA
dreimac-0.3.2.dist-info/WHEEL
dreimac-0.3.2.dist-info/top_level.txt
dreimac-0.3.2.dist-info/RECORD
