Metadata-Version: 2.1
Name: dreimac
Version: 0.3.2
Summary: DREiMac: Dimensionality reduction with Eilenberg-MacLane coordinates
Author-email: "Jose A. Perea" <joperea@gmail.com>, Luis Scoccola <luis.scoccola@gmail.com>, Chris Tralie <chris.tralie@gmail.com>
Maintainer-email: "Jose A. Perea" <joperea@gmail.com>, Luis Scoccola <luis.scoccola@gmail.com>, Chris Tralie <chris.tralie@gmail.com>
Project-URL: Homepage, https://dreimac.scikit-tda.org
Project-URL: Documentation, https://dreimac.scikit-tda.org
Project-URL: Repository, https://github.com/scikit-tda/DREiMac
Project-URL: Issues, https://github.com/scikit-tda/DREiMac/issues
Keywords: dimensionality reduction,topological data analysis
Classifier: Intended Audience :: Science/Research
Classifier: Intended Audience :: Education
Classifier: Intended Audience :: Financial and Insurance Industry
Classifier: Intended Audience :: Healthcare Industry
Classifier: Topic :: Scientific/Engineering :: Information Analysis
Classifier: Topic :: Scientific/Engineering :: Mathematics
Classifier: Programming Language :: Python :: 3.8
Classifier: Programming Language :: Python :: 3.9
Classifier: Programming Language :: Python :: 3.10
Classifier: Programming Language :: Python :: 3.11
Classifier: License :: OSI Approved :: Apache Software License
Requires-Python: <3.12,>=3.8
License-File: LICENSE
Requires-Dist: matplotlib>=3.6
Requires-Dist: numba>=0.56
Requires-Dist: numpy>=1.23
Requires-Dist: persim>=0.3
Requires-Dist: ripser>=0.6
Requires-Dist: scipy>=1.10
Provides-Extra: docs
Requires-Dist: sphinx; extra == "docs"
Requires-Dist: sphinx-rtd-theme; extra == "docs"
Requires-Dist: numpydoc; extra == "docs"
Requires-Dist: ipykernel; extra == "docs"
Requires-Dist: nbsphinx; extra == "docs"
Provides-Extra: testing
Requires-Dist: pytest; extra == "testing"
Requires-Dist: pytest-cov; extra == "testing"
